ggtransfer/__init__.py
ggtransfer/__main__.py
ggtransfer/_exceptions.py
ggtransfer/_receive.py
ggtransfer/_send.py
gg_transfer-0.2.13.dist-info/LICENSE
gg_transfer-0.2.13.dist-info/METADATA
gg_transfer-0.2.13.dist-info/WHEEL
gg_transfer-0.2.13.dist-info/entry_points.txt
gg_transfer-0.2.13.dist-info/top_level.txt
gg_transfer-0.2.13.dist-info/RECORD
