Metadata-Version: 2.1
Name: gg-transfer
Version: 0.2.13
Summary: FSK text/file transfer utility
Author-email: Matteo Tenca <matteo.tenca@gmail.com>
Project-URL: Homepage, https://github.com/matteotenca/gg-transfer
Classifier: Development Status :: 5 - Production/Stable
Classifier: Intended Audience :: Developers
Classifier: Intended Audience :: Information Technology
Classifier: Programming Language :: Python :: 3.8
Classifier: Programming Language :: Python :: 3.9
Classifier: Programming Language :: Python :: 3.10
Classifier: Programming Language :: Python :: 3.11
Classifier: Programming Language :: Python :: 3.12
Classifier: Programming Language :: Python :: 3.13
Classifier: Topic :: Software Development :: Libraries :: Python Modules
Classifier: Topic :: System :: Networking
Classifier: Topic :: Communications
Classifier: License :: OSI Approved :: GNU General Public License v3 or later (GPLv3+)
Requires-Python: >=3.8
License-File: LICENSE
Requires-Dist: sounddevice
Requires-Dist: ggwave-wheels>=0.4.2.3
